__init__.py
fjml/__init__.py
fjml/cli_tooling.py
fjml/constants.py
fjml/data_types.py
fjml/error_types.py
fjml/object_enums.py
fjml/operation_classes.py
fjml/type_checker.py
fjml/utils.py
fjml/compiler/__init__.py
fjml/compiler/checks.py
fjml/compiler/compiler.py
fjml/constant_controls/__init__.py
fjml/constant_controls/custom_responsive_row.py
fjml/constant_controls/size_aware_control.py
fjml/display/__init__.py
fjml/display/builder.py
fjml/display/renderer.py
fjml/registry/__init__.py
fjml/registry/control_register.py
fjml-0.0.5.dist-info/LICENSE
fjml-0.0.5.dist-info/METADATA
fjml-0.0.5.dist-info/WHEEL
fjml-0.0.5.dist-info/entry_points.txt
fjml-0.0.5.dist-info/top_level.txt
fjml-0.0.5.dist-info/RECORD
