Metadata-Version: 2.1
Name: fjml
Version: 0.0.5
Summary: A JSON based markup language which translates JSON files into Flet UI 
Author-email: loafthecomputerphile <loafdcomputerphile@gmail.com>
Project-URL: Homepage, https://github.com/loafthecomputerphile/fjml
Project-URL: Issues, https://github.com/loafthecomputerphile/fjml/issues
Keywords: flet,gui,markup language
Classifier: Programming Language :: Python :: 3.8
Classifier: License :: OSI Approved :: Apache Software License
Classifier: Operating System :: OS Independent
Requires-Python: >=3.8
License-File: LICENSE
Requires-Dist: flet >=0.22.0
Requires-Dist: typing-extensions >=4.11.0
Requires-Dist: dill >=0.3.8
